odoo_addons_path/__init__.py
odoo_addons_path/cli.py
odoo_addons_path/detector.py
odoo_addons_path/main.py
odoo_addons_path-1.0.1.dist-info/METADATA
odoo_addons_path-1.0.1.dist-info/WHEEL
odoo_addons_path-1.0.1.dist-info/entry_points.txt
odoo_addons_path-1.0.1.dist-info/licenses/LICENSE
odoo_addons_path-1.0.1.dist-info/RECORD
