Metadata-Version: 2.4
Name: odoo-addons-path
Version: 1.0.1
Summary: Create the ultimate Odoo addons_path constructor
Project-URL: Repository, https://github.com/trobz/odoo-addons-path
Author-email: trisdoan <doanminhtri8183@gmail.com>
License-File: LICENSE
Keywords: python
Requires-Python: <4.0,>=3.10
Requires-Dist: pyyaml
Requires-Dist: typer>=0.19.2
